azure/mgmt/iothub/__init__.py
azure/mgmt/iothub/_configuration.py
azure/mgmt/iothub/_iot_hub_client.py
azure/mgmt/iothub/_serialization.py
azure/mgmt/iothub/_version.py
azure/mgmt/iothub/models.py
azure/mgmt/iothub/py.typed
azure/mgmt/iothub/aio/__init__.py
azure/mgmt/iothub/aio/_configuration.py
azure/mgmt/iothub/aio/_iot_hub_client.py
azure/mgmt/iothub/v2019_03_22/__init__.py
azure/mgmt/iothub/v2019_03_22/_configuration.py
azure/mgmt/iothub/v2019_03_22/_iot_hub_client.py
azure/mgmt/iothub/v2019_03_22/_patch.py
azure/mgmt/iothub/v2019_03_22/_version.py
azure/mgmt/iothub/v2019_03_22/py.typed
azure/mgmt/iothub/v2019_03_22/aio/__init__.py
azure/mgmt/iothub/v2019_03_22/aio/_configuration.py
azure/mgmt/iothub/v2019_03_22/aio/_iot_hub_client.py
azure/mgmt/iothub/v2019_03_22/aio/_patch.py
azure/mgmt/iothub/v2019_03_22/aio/operations/__init__.py
azure/mgmt/iothub/v2019_03_22/aio/operations/_certificates_operations.py
azure/mgmt/iothub/v2019_03_22/aio/operations/_iot_hub_operations.py
azure/mgmt/iothub/v2019_03_22/aio/operations/_iot_hub_resource_operations.py
azure/mgmt/iothub/v2019_03_22/aio/operations/_operations.py
azure/mgmt/iothub/v2019_03_22/aio/operations/_patch.py
azure/mgmt/iothub/v2019_03_22/aio/operations/_resource_provider_common_operations.py
azure/mgmt/iothub/v2019_03_22/models/__init__.py
azure/mgmt/iothub/v2019_03_22/models/_iot_hub_client_enums.py
azure/mgmt/iothub/v2019_03_22/models/_models_py3.py
azure/mgmt/iothub/v2019_03_22/models/_patch.py
azure/mgmt/iothub/v2019_03_22/operations/__init__.py
azure/mgmt/iothub/v2019_03_22/operations/_certificates_operations.py
azure/mgmt/iothub/v2019_03_22/operations/_iot_hub_operations.py
azure/mgmt/iothub/v2019_03_22/operations/_iot_hub_resource_operations.py
azure/mgmt/iothub/v2019_03_22/operations/_operations.py
azure/mgmt/iothub/v2019_03_22/operations/_patch.py
azure/mgmt/iothub/v2019_03_22/operations/_resource_provider_common_operations.py
azure/mgmt/iothub/v2019_07_01_preview/__init__.py
azure_mgmt_iothub-4.0.0.dist-info/LICENSE
azure_mgmt_iothub-4.0.0.dist-info/METADATA
azure_mgmt_iothub-4.0.0.dist-info/WHEEL
azure_mgmt_iothub-4.0.0.dist-info/top_level.txt
azure_mgmt_iothub-4.0.0.dist-info/RECORD
